send_text.py
send_text-1.0.1.dist-info/LICENSE
send_text-1.0.1.dist-info/METADATA
send_text-1.0.1.dist-info/WHEEL
send_text-1.0.1.dist-info/top_level.txt
send_text-1.0.1.dist-info/RECORD
