Metadata-Version: 2.1
Name: send-text
Version: 1.0.1
Summary: A simple Python module to send text messages
Home-page: https://github.com/Pacil142857/send_text
Author: Austin McGregor
Author-email: austinmcgregor2@gmail.com
License: MIT
Platform: UNKNOWN
Classifier: License :: OSI Approved :: MIT License
Classifier: Programming Language :: Python :: 3
Classifier: Programming Language :: Python :: 3.7
Requires-Python: >=3.5
